MANIFEST.in
README.md
setup.cfg
setup.py
orcas/__init__.py
orcas/cli.py
orcas/face_tool.py
orcas/logger.py
orcas/storage.py
orcas.egg-info/PKG-INFO
orcas.egg-info/SOURCES.txt
orcas.egg-info/dependency_links.txt
orcas.egg-info/entry_points.txt
orcas.egg-info/not-zip-safe
orcas.egg-info/requires.txt
orcas.egg-info/top_level.txt
orcas/data/dlib_face_recognition_resnet_model_v1.dat
orcas/data/shape_predictor_5_face_landmarks.dat