Metadata-Version: 1.0
Name: orcas
Version: 1.1.2
Summary: Classify the images in your photo album into suitable destinations.
Home-page: http://github.com/ahmdrz/orcas
Author: Ahmadreza Zibaei
Author-email: ahmadrezazibaei@hotmail.com
License: MIT
Platform: UNKNOWN
